[
{"BuildingID":33,"BuildingName":"Center Street North","RoomNumber":"CSN102A","Gender":"Female","Capacity":"4 person","Term":"2022 Spring","LastUpdated":"2021-11-06 20:30:03"},
{"BuildingID":33,"BuildingName":"Center Street North","RoomNumber":"CSN107A","Gender":"Male","Capacity":"4 person","Term":"2022 Spring","LastUpdated":"2021-11-06 20:30:03"},
{"BuildingID":34,"BuildingName":"Center Street South","RoomNumber":"CSS002C","Gender":"Male","Capacity":"4 person","Term":"2022 Spring","LastUpdated":"2021-11-06 20:30:03"},
{"BuildingID":34,"BuildingName":"Center Street South","RoomNumber":"CSS311C","Gender":"Neutral","Capacity":"4 person","Term":"2022 Spring","LastUpdated":"2021-11-06 20:30:03"},
{"BuildingID":35,"BuildingName":"Crecine","RoomNumber":"CRE503D","Gender":"Female","Capacity":"4 person","Term":"2022 Spring","LastUpdated":"2021-11-06 20:30:03"},
{"BuildingID":36,"BuildingName":"Eighth Street East","RoomNumber":"ESE118A","Gender":"Female","Capacity":"4 person","Term":"2022 Spring","LastUpdated":"2021-11-06 20:30:03"},
{"BuildingID":36,"BuildingName":"Eighth Street East","RoomNumber":"ESE317D","Gender":"Female","Capacity":"4 person","Term":"2022 Spring","LastUpdated":"2021-11-06 20:30:03"},
{"BuildingID":37,"BuildingName":"Eighth Street South","RoomNumber":"ESS111D","Gender":"Female","Capacity":"4 person","Term":"2022 Spring","LastUpdated":"2021-11-06 20:30:03"},
{"BuildingID":23,"BuildingName":"Graduate Living Center","RoomNumber":"GLC218D","Gender":"Female","Capacity":"4 person","Term":"2022 Spring","LastUpdated":"2021-11-06 20:30:03"},
{"BuildingID":23,"BuildingName":"Graduate Living Center","RoomNumber":"GLC316A","Gender":"Male","Capacity":"4 person","Term":"2022 Spring","LastUpdated":"2021-11-06 20:30:03"},
{"BuildingID":23,"BuildingName":"Graduate Living Center","RoomNumber":"GLC319A","Gender":"Male","Capacity":"4 person","Term":"2022 Spring","LastUpdated":"2021-11-06 20:30:03"},
{"BuildingID":23,"BuildingName":"Graduate Living Center","RoomNumber":"GLC320A","Gender":"Female","Capacity":"4 person","Term":"2022 Spring","LastUpdated":"2021-11-06 20:30:03"},
{"BuildingID":23,"BuildingName":"Graduate Living Center","RoomNumber":"GLC402A","Gender":"Female","Capacity":"4 person","Term":"2022 Spring","LastUpdated":"2021-11-06 20:30:03"},
{"BuildingID":23,"BuildingName":"Graduate Living Center","RoomNumber":"GLC402D","Gender":"Female","Capacity":"4 person","Term":"2022 Spring","LastUpdated":"2021-11-06 20:30:03"},
{"BuildingID":23,"BuildingName":"Graduate Living Center","RoomNumber":"GLC508D","Gender":"Male","Capacity":"4 person","Term":"2022 Spring","LastUpdated":"2021-11-06 20:30:03"},
{"BuildingID":23,"BuildingName":"Graduate Living Center","RoomNumber":"GLC509C","Gender":"Male","Capacity":"4 person","Term":"2022 Spring","LastUpdated":"2021-11-06 20:30:03"},
{"BuildingID":23,"BuildingName":"Graduate Living Center","RoomNumber":"GLC512B","Gender":"Female","Capacity":"4 person","Term":"2022 Spring","LastUpdated":"2021-11-06 20:30:03"},
{"BuildingID":23,"BuildingName":"Graduate Living Center","RoomNumber":"GLC518D","Gender":"Female","Capacity":"4 person","Term":"2022 Spring","LastUpdated":"2021-11-06 20:30:03"},
{"BuildingID":23,"BuildingName":"Graduate Living Center","RoomNumber":"GLC613D","Gender":"Male","Capacity":"4 person","Term":"2022 Spring","LastUpdated":"2021-11-06 20:30:03"},
{"BuildingID":23,"BuildingName":"Graduate Living Center","RoomNumber":"GLC615B","Gender":"Female","Capacity":"4 person","Term":"2022 Spring","LastUpdated":"2021-11-06 20:30:03"},
{"BuildingID":23,"BuildingName":"Graduate Living Center","RoomNumber":"GLC617C","Gender":"Male","Capacity":"4 person","Term":"2022 Spring","LastUpdated":"2021-11-06 20:30:03"},
{"BuildingID":23,"BuildingName":"Graduate Living Center","RoomNumber":"GLC618A","Gender":"Male","Capacity":"4 person","Term":"2022 Spring","LastUpdated":"2021-11-06 20:30:03"},
{"BuildingID":23,"BuildingName":"Graduate Living Center","RoomNumber":"GLC618D","Gender":"Male","Capacity":"4 person","Term":"2022 Spring","LastUpdated":"2021-11-06 20:30:03"},
{"BuildingID":44,"BuildingName":"Maulding","RoomNumber":"MLD228E","Gender":"Male","Capacity":"6 person","Term":"2022 Spring","LastUpdated":"2021-11-06 20:30:03"},
{"BuildingID":44,"BuildingName":"Maulding","RoomNumber":"MLD325E","Gender":"Male","Capacity":"6 person","Term":"2022 Spring","LastUpdated":"2021-11-06 20:30:03"},
{"BuildingID":44,"BuildingName":"Maulding","RoomNumber":"MLD401E","Gender":"Male","Capacity":"6 person","Term":"2022 Spring","LastUpdated":"2021-11-06 20:30:03"},
{"BuildingID":44,"BuildingName":"Maulding","RoomNumber":"MLD413B","Gender":"Male","Capacity":"2 person","Term":"2022 Spring","LastUpdated":"2021-11-06 20:30:03"},
{"BuildingID":15,"BuildingName":"North Avenue North","RoomNumber":"NAN0815C","Gender":"Neutral","Capacity":"4 person","Term":"2022 Spring","LastUpdated":"2021-11-06 20:30:03"},
{"BuildingID":16,"BuildingName":"North Avenue South","RoomNumber":"NAS0526A","Gender":"Male","Capacity":"4 person","Term":"2022 Spring","LastUpdated":"2021-11-06 20:30:03"},
{"BuildingID":25,"BuildingName":"Tenth and Home B","RoomNumber":"THB204A","Gender":"Male","Capacity":"2 person","Term":"2022 Spring","LastUpdated":"2021-11-06 20:30:03"},
{"BuildingID":25,"BuildingName":"Tenth and Home B","RoomNumber":"THB510A","Gender":"Female","Capacity":"2 person","Term":"2022 Spring","LastUpdated":"2021-11-06 20:30:03"},
{"BuildingID":25,"BuildingName":"Tenth and Home B","RoomNumber":"THB706B","Gender":"Female","Capacity":"2 person","Term":"2022 Spring","LastUpdated":"2021-11-06 20:30:03"},
{"BuildingID":25,"BuildingName":"Tenth and Home B","RoomNumber":"THB708B","Gender":"Male","Capacity":"2 person","Term":"2022 Spring","LastUpdated":"2021-11-06 20:30:03"},
{"BuildingID":27,"BuildingName":"Tenth and Home D","RoomNumber":"THD107A","Gender":"Male","Capacity":"2 person","Term":"2022 Spring","LastUpdated":"2021-11-06 20:30:03"},
{"BuildingID":27,"BuildingName":"Tenth and Home D","RoomNumber":"THD310A","Gender":"Female","Capacity":"2 person","Term":"2022 Spring","LastUpdated":"2021-11-06 20:30:03"},
{"BuildingID":27,"BuildingName":"Tenth and Home D","RoomNumber":"THD406A","Gender":"Male","Capacity":"2 person","Term":"2022 Spring","LastUpdated":"2021-11-06 20:30:03"},
{"BuildingID":28,"BuildingName":"Tenth and Home E","RoomNumber":"THE202A","Gender":"Male","Capacity":"2 person","Term":"2022 Spring","LastUpdated":"2021-11-06 20:30:03"},
{"BuildingID":28,"BuildingName":"Tenth and Home E","RoomNumber":"THE306A","Gender":"Female","Capacity":"2 person","Term":"2022 Spring","LastUpdated":"2021-11-06 20:30:03"},
{"BuildingID":28,"BuildingName":"Tenth and Home E","RoomNumber":"THE402B","Gender":"Female","Capacity":"2 person","Term":"2022 Spring","LastUpdated":"2021-11-06 20:30:03"},
{"BuildingID":28,"BuildingName":"Tenth and Home E","RoomNumber":"THE407A","Gender":"Male","Capacity":"2 person","Term":"2022 Spring","LastUpdated":"2021-11-06 20:30:03"},
{"BuildingID":28,"BuildingName":"Tenth and Home E","RoomNumber":"THE411A","Gender":"Male","Capacity":"2 person","Term":"2022 Spring","LastUpdated":"2021-11-06 20:30:03"},
{"BuildingID":29,"BuildingName":"Tenth and Home F","RoomNumber":"THF115B","Gender":"Male","Capacity":"2 person","Term":"2022 Spring","LastUpdated":"2021-11-06 20:30:03"},
{"BuildingID":29,"BuildingName":"Tenth and Home F","RoomNumber":"THF216B","Gender":"Male","Capacity":"2 person","Term":"2022 Spring","LastUpdated":"2021-11-06 20:30:03"},
{"BuildingID":29,"BuildingName":"Tenth and Home F","RoomNumber":"THF306B","Gender":"Male","Capacity":"2 person","Term":"2022 Spring","LastUpdated":"2021-11-06 20:30:03"},
{"BuildingID":29,"BuildingName":"Tenth and Home F","RoomNumber":"THF309A","Gender":"Female","Capacity":"2 person","Term":"2022 Spring","LastUpdated":"2021-11-06 20:30:03"},
{"BuildingID":29,"BuildingName":"Tenth and Home F","RoomNumber":"THF313A","Gender":"Male","Capacity":"2 person","Term":"2022 Spring","LastUpdated":"2021-11-06 20:30:03"},
{"BuildingID":29,"BuildingName":"Tenth and Home F","RoomNumber":"THF317A","Gender":"Female","Capacity":"2 person","Term":"2022 Spring","LastUpdated":"2021-11-06 20:30:03"},
{"BuildingID":29,"BuildingName":"Tenth and Home F","RoomNumber":"THF318B","Gender":"Male","Capacity":"2 person","Term":"2022 Spring","LastUpdated":"2021-11-06 20:30:03"},
{"BuildingID":29,"BuildingName":"Tenth and Home F","RoomNumber":"THF401B","Gender":"Male","Capacity":"2 person","Term":"2022 Spring","LastUpdated":"2021-11-06 20:30:03"},
{"BuildingID":30,"BuildingName":"Tenth and Home G","RoomNumber":"THG111B","Gender":"Male","Capacity":"2 person","Term":"2022 Spring","LastUpdated":"2021-11-06 20:30:03"},
{"BuildingID":30,"BuildingName":"Tenth and Home G","RoomNumber":"THG202B","Gender":"Male","Capacity":"2 person","Term":"2022 Spring","LastUpdated":"2021-11-06 20:30:03"},
{"BuildingID":30,"BuildingName":"Tenth and Home G","RoomNumber":"THG209B","Gender":"Male","Capacity":"2 person","Term":"2022 Spring","LastUpdated":"2021-11-06 20:30:03"},
{"BuildingID":30,"BuildingName":"Tenth and Home G","RoomNumber":"THG210A","Gender":"Male","Capacity":"2 person","Term":"2022 Spring","LastUpdated":"2021-11-06 20:30:03"},
{"BuildingID":30,"BuildingName":"Tenth and Home G","RoomNumber":"THG304A","Gender":"Male","Capacity":"2 person","Term":"2022 Spring","LastUpdated":"2021-11-06 20:30:03"},
{"BuildingID":46,"BuildingName":"Zbar (SSA)","RoomNumber":"ZBR201A","Gender":"Male","Capacity":"6 person","Term":"2022 Spring","LastUpdated":"2021-11-06 20:30:03"}
]